{
  "id": "material-properties",
  "title": "תכונות חומרים",
  "metadata": {
    "description": "תכונות פיזיקליות של חומרים: מוליכות חשמלית ותרמית, קשיות, שקיפות ומסיסות. שיעור אינטראקטיבי במדעים לכיתה ז'.",
    "keywords": ["תכונות חומרים", "מוליכות חשמל", "מוליכות חום", "קשיות", "שקיפות", "מסיסות", "מדעים כיתה ז", "בחירת חומרים"]
  },
  "blocks": [
    {
      "type": "hero",
      "title": "תכונות חומרים",
      "subtitle": "איך מזהים חומר? לכל חומר יש תכונות ייחודיות שמגדירות אותו"
    },
    {
      "type": "introduction_block",
      "title": "למה חשוב להכיר תכונות?",
      "icon": "magnifying-glass-tilted-left",
      "theme": "primary-blue",
      "content": [
        {
          "type": "text",
          "size": "lg",
          "content": "כשאנחנו רוצים לבנות משהו, אנחנו צריכים לבחור את {b}החומר המתאים{/b}. הבחירה תלויה ב{b}תכונות החומר{/b}."
        },
        {
          "type": "text",
          "size": "md",
          "content": "למשל: למה חוטי חשמל עשויים מנחושת ולא מעץ? למה חלונות עשויים מזכוכית ולא מברזל?"
        }
      ]
    },
    {
      "type": "grid_cards",
      "title": "מוליכות חשמלית",
      "cols": 2,
      "cards": [
        {
          "title": "מוליכים",
          "icon": "high-voltage",
          "content": [
            {
              "type": "p",
              "content": "חומרים שמאפשרים לזרם חשמלי לעבור דרכם."
            },
            {
              "type": "callout",
              "variant": "emerald",
              "content": [
                {
                  "type": "p",
                  "content": "{b}דוגמאות:{/b}\n• נחושת\n• ברזל\n• אלומיניום\n• מי מלח"
                }
              ]
            }
          ],
          "variant": "emerald"
        },
        {
          "title": "מבודדים",
          "icon": "shield",
          "content": [
            {
              "type": "p",
              "content": "חומרים שלא מאפשרים לזרם חשמלי לעבור."
            },
            {
              "type": "callout",
              "variant": "blue",
              "content": [
                {
                  "type": "p",
                  "content": "{b}דוגמאות:{/b}\n• פלסטיק\n• גומי\n• עץ יבש\n• זכוכית"
                }
              ]
            }
          ],
          "variant": "blue"
        }
      ]
    },
    {
      "type": "tip_box",
      "title": "כבל חשמלי - שילוב מושלם",
      "icon": "electric-plug",
      "variant": "info",
      "content": "כבל חשמלי בנוי משני חומרים:",
      "steps": [
        "{b}ליבה מנחושת{/b} - מוליכה את הזרם ביעילות",
        "{b}מעטפת פלסטיק{/b} - מבודדת ומגינה מפני התחשמלות",
        "זו דוגמה לבחירת חומרים על פי תכונותיהם!"
      ]
    },
    {
      "type": "grid_cards",
      "title": "מוליכות חום",
      "cols": 2,
      "cards": [
        {
          "title": "מוליכי חום טובים",
          "icon": "fire",
          "content": [
            {
              "type": "p",
              "content": "חומרים שמעבירים חום {b}מהר{/b}."
            },
            {
              "type": "callout",
              "variant": "orange",
              "content": [
                {
                  "type": "p",
                  "content": "{b}דוגמאות:{/b}\n• מתכות (אלומיניום, נחושת)\n\n{b}שימוש:{/b} סירי בישול עשויים מתכת כדי להעביר חום מהאש למזון"
                }
              ]
            }
          ],
          "variant": "orange"
        },
        {
          "title": "מבודדי חום",
          "icon": "snowflake",
          "content": [
            {
              "type": "p",
              "content": "חומרים שמעבירים חום {b}לאט{/b}."
            },
            {
              "type": "callout",
              "variant": "cyan",
              "content": [
                {
                  "type": "p",
                  "content": "{b}דוגמאות:{/b}\n• עץ, פלסטיק, קלקר\n• אוויר, צמר\n\n{b}שימוש:{/b} ידיות סירים עשויות פלסטיק כדי לא להיכוות"
                }
              ]
            }
          ],
          "variant": "cyan"
        }
      ]
    },
    {
      "type": "concept_explainer",
      "title": "קשיות",
      "icon": "gem-stone",
      "variant": "purple",
      "intro": "קשיות היא יכולת של חומר להתנגד לשריטה או לחריצה.",
      "explanation": "{b}מבחן החריצה:{/b}\nאם חומר A מצליח לחרוץ את חומר B, אז A {b}קשה יותר{/b} מ-B.\n\n{b}דוגמאות לפי קשיות (מהרך לקשה):{/b}\n• טלק (הכי רך)\n• ציפורן\n• זכוכית\n• פלדה\n• יהלום (הכי קשה בטבע)",
      "conclusion": "יהלום יכול לחרוץ כל חומר אחר, ולכן משתמשים בו לחיתוך זכוכית ולקדיחה."
    },
    {
      "type": "grid_cards",
      "title": "תכונות אופטיות",
      "cols": 3,
      "cards": [
        {
          "title": "שקוף",
          "icon": "window",
          "content": [
            {
              "type": "p",
              "content": "אור עובר לגמרי."
            },
            {
              "type": "callout",
              "variant": "blue",
              "content": [
                {
                  "type": "p",
                  "content": "זכוכית חלון, מים נקיים, אוויר"
                }
              ]
            }
          ],
          "variant": "blue"
        },
        {
          "title": "חצי-שקוף",
          "icon": "cloud",
          "content": [
            {
              "type": "p",
              "content": "אור עובר חלקית."
            },
            {
              "type": "callout",
              "variant": "amber",
              "content": [
                {
                  "type": "p",
                  "content": "זכוכית חלבית, נייר דק, ערפל"
                }
              ]
            }
          ],
          "variant": "amber"
        },
        {
          "title": "אטום",
          "icon": "brick",
          "content": [
            {
              "type": "p",
              "content": "אור לא עובר כלל."
            },
            {
              "type": "callout",
              "variant": "purple",
              "content": [
                {
                  "type": "p",
                  "content": "עץ, מתכת, קרטון, אבן"
                }
              ]
            }
          ],
          "variant": "purple"
        }
      ]
    },
    {
      "type": "concept_explainer",
      "title": "ברק",
      "icon": "star",
      "variant": "amber",
      "intro": "ברק הוא האופן שבו פני השטח של חומר מחזירים אור.",
      "explanation": "{b}ברק מתכתי:{/b}\nמתכות מחזירות אור בצורה ייחודית ומבריקה.\nדוגמאות: זהב, כסף, נחושת מצוחצחת\n\n{b}ברק מט (חסר ברק):{/b}\nחומרים שאינם מחזירים אור בצורה חזקה.\nדוגמאות: גיר, פחם, עץ לא מלוטש",
      "conclusion": "תכונת הברק עוזרת לזהות מתכות ולהבדיל בינן לבין חומרים אחרים."
    },
    {
      "type": "concept_explainer",
      "title": "מסיסות",
      "icon": "droplet",
      "variant": "blue",
      "intro": "מסיסות היא היכולת של חומר להתמוסס בתוך חומר אחר וליצור תערובת אחידה (תמיסה).",
      "explanation": "{b}דוגמאות:{/b}\n• סוכר מתמוסס במים ✓\n• מלח מתמוסס במים ✓\n• שמן לא מתמוסס במים ✗\n• חול לא מתמוסס במים ✗\n\n{b}גורמים המשפיעים:{/b}\n• סוג החומר\n• טמפרטורה (בדרך כלל חום מגביר מסיסות)",
      "conclusion": "כשסוכר מתמוסס במים, הוא לא נעלם - הוא מתפזר בין מולקולות המים!"
    },
    {
      "type": "scientific_table",
      "title": "סיכום תכונות חומרים נפוצים",
      "headers": ["חומר", "מוליך חשמל?", "מוליך חום?", "קשיות"],
      "rows": [
        ["נחושת", "כן (מצוין)", "כן (מצוין)", "בינונית"],
        ["ברזל/פלדה", "כן", "כן", "גבוהה"],
        ["זכוכית", "לא", "לא", "גבוהה"],
        ["פלסטיק", "לא", "לא", "נמוכה-בינונית"],
        ["עץ", "לא", "לא", "בינונית"],
        ["יהלום", "לא", "כן!", "הגבוהה ביותר"]
      ],
      "variant": "blue",
      "note": "יהלום הוא חריג מעניין: מבודד חשמלי אבל מוליך חום מצוין!"
    },
    {
      "type": "thinking_question",
      "title": "שאלה למחשבה",
      "question": "למה כלי מטבח (סירים, מחבתות) עשויים ממתכת עם ידיות מפלסטיק או עץ?",
      "answer": "גוף הסיר צריך להיות ממתכת כי:\n• מתכת {b}מוליכה חום{/b} טוב - מעבירה את החום מהכיריים למזון\n\nהידיות צריכות להיות מפלסטיק/עץ כי:\n• פלסטיק ועץ {b}מבודדי חום{/b} - לא מעבירים את החום ליד\n• מונעים כוויות!\n\nזו דוגמה מצוינת לבחירת חומרים לפי תכונותיהם."
    },
    {
      "type": "enrichment",
      "title": "חומרים מתקדמים",
      "icon": "rocket",
      "content": [
        {
          "type": "p",
          "content": "מדענים מפתחים חומרים חדשים עם תכונות מיוחדות:"
        },
        {
          "type": "callout",
          "variant": "purple",
          "content": [
            {
              "type": "p",
              "content": "• {b}גרפן{/b} - חזק פי 200 מפלדה אבל דק כמו אטום אחד!\n• {b}אירוג'ל{/b} - מבודד חום מצוין, 99% אוויר\n• {b}סיבי פחמן{/b} - קלים וחזקים, משמשים במטוסים ומכוניות מירוץ"
            }
          ]
        }
      ]
    },
    {
      "type": "quiz"
    }
  ]
}
